texbrix/__init__.py
texbrix/__main__.py
texbrix/default_template.dat
texbrix/mathbrik.py
texbrix/texbrik.py
TeXBriX-0.2.10.dist-info/LICENSE
TeXBriX-0.2.10.dist-info/METADATA
TeXBriX-0.2.10.dist-info/WHEEL
TeXBriX-0.2.10.dist-info/entry_points.txt
TeXBriX-0.2.10.dist-info/top_level.txt
TeXBriX-0.2.10.dist-info/RECORD
