Metadata-Version: 2.1
Name: TeXBriX
Version: 0.2.10
Summary: A granular approach to LaTeX
Home-page: http://github.com/leopoldfajtak/texbrix
Author: Leopold Fajtak
Author-email: leopold@fajtak.at
License: GPLv3
Keywords: mathematics dependencies layout filestructure
Platform: UNKNOWN
Classifier: Development Status :: 3 - Alpha
Classifier: Environment :: Console
Classifier: Intended Audience :: Science/Research
Classifier: Natural Language :: English
Classifier: Operating System :: POSIX :: Linux
Classifier: Programming Language :: Python :: 3
Classifier: Topic :: Text Processing :: Markup :: LaTeX
